pyramid_jwt/__init__.py
pyramid_jwt/policy.py
pyramid_jwt-1.6.0.dist-info/LICENSE
pyramid_jwt-1.6.0.dist-info/METADATA
pyramid_jwt-1.6.0.dist-info/WHEEL
pyramid_jwt-1.6.0.dist-info/top_level.txt
pyramid_jwt-1.6.0.dist-info/zip-safe
pyramid_jwt-1.6.0.dist-info/RECORD
