Metadata-Version: 2.1
Name: pyramid-jwt
Version: 1.6.0
Summary: JWT authentication policy for Pyramid
Home-page: https://github.com/wichert/pyramid_jwt
Author: Wichert Akkerman
Author-email: wichert@wiggy.net
License: BSD
Keywords: Pyramid JWT authentication security
Platform: any
Classifier: Intended Audience :: Developers
Classifier: License :: DFSG approved
Classifier: License :: OSI Approved :: BSD License
Classifier: Operating System :: OS Independent
Classifier: Programming Language :: Python :: 3
Classifier: Programming Language :: Python :: 3.6
Classifier: Programming Language :: Python :: 3.7
Classifier: Programming Language :: Python :: 3.8
Classifier: Topic :: Software Development :: Libraries :: Python Modules
Requires-Dist: pyramid
Requires-Dist: PyJWT
Provides-Extra: testing
Requires-Dist: WebTest ; extra == 'testing'
Requires-Dist: pytest ; extra == 'testing'
Requires-Dist: pytest-freezegun ; extra == 'testing'
